new2.py
first_app-0.0.10.dist-info/METADATA
first_app-0.0.10.dist-info/WHEEL
first_app-0.0.10.dist-info/top_level.txt
first_app-0.0.10.dist-info/RECORD
