Metadata-Version: 2.1
Name: first-app
Version: 0.0.10
Summary: my first app
Home-page: UNKNOWN
Author: UNKNOWN
Author-email: UNKNOWN
License: UNKNOWN
Platform: UNKNOWN
